tests/test_umicount.py
tests/test_umicount_umi_correction.py
tests/test_umicount_write_output.py
tests/test_umiextract_process_entry.py
tests/test_umiextract_process_fastq.py
tests/test_umiextract_utility_functions.py
umite/__init__.py
umite/cli.py
umite/umicount.py
umite/umiextract.py
umite-0.1.1.dist-info/licenses/LICENSE
umite-0.1.1.dist-info/METADATA
umite-0.1.1.dist-info/WHEEL
umite-0.1.1.dist-info/entry_points.txt
umite-0.1.1.dist-info/top_level.txt
umite-0.1.1.dist-info/RECORD
