Metadata-Version: 2.4
Name: umite
Version: 0.1.1
Summary: UMI counting tool for SmartSeq3 libraries
Author-email: Leo Förster <leoforster@gmail.com>, Enrico Frigoli <enrico.frigoli@dkfz-heidelberg.de>, Xiaoyu Sun <binggans@hotmail.com>, Angela Goncalves <a.goncalves@dkfz-heidelberg.de>, Ana Martin-Villalba <a.martin-villalba@dkfz-heidelberg.de>
Maintainer-email: Leo Förster <leoforster@gmail.com>
License-Expression: GPL-3.0-or-later
Keywords: biology,bioinformatics,single cell,transcriptomics,smartseq3
Classifier: Topic :: Scientific/Engineering :: Bio-Informatics
Requires-Python: >=3.7
License-File: LICENSE
Requires-Dist: HTSeq
Requires-Dist: regex
Requires-Dist: RapidFuzz
Provides-Extra: tests
Requires-Dist: pytest>=5; extra == "tests"
Provides-Extra: workflow
Requires-Dist: snakemake>=8; extra == "workflow"
Dynamic: license-file
